tpds_utils_config/__init__.py
tpds_utils_config/config.py
tpds_utils_config-0.0.1.dist-info/LICENSE
tpds_utils_config-0.0.1.dist-info/METADATA
tpds_utils_config-0.0.1.dist-info/WHEEL
tpds_utils_config-0.0.1.dist-info/top_level.txt
tpds_utils_config-0.0.1.dist-info/RECORD
